coupling/__init__.py
coupling/archive.py
coupling/cmd.py
coupling/deprecated.py
coupling/dict.py
coupling/fs.py
coupling/jsonpath.py
coupling/log.py
coupling/mail.py
coupling/misc.py
coupling/module.py
coupling/psexec.py
coupling/regex.py
coupling/text.py
coupling/xml.py
coupling/net/__init__.py
coupling/net/ftp.py
coupling/net/ssh.py
coupling/net/util.py
coupling/net/xmlrpc.py
coupling/pattern/__init__.py
coupling/pattern/observer.py
coupling/pattern/singleton.py
coupling/ui/__init__.py
coupling/ui/cli.py
coupling-1.1.1.dist-info/LICENSE
coupling-1.1.1.dist-info/METADATA
coupling-1.1.1.dist-info/WHEEL
coupling-1.1.1.dist-info/top_level.txt
coupling-1.1.1.dist-info/RECORD
