Metadata-Version: 2.1
Name: coupling
Version: 1.1.1
Summary: Util library.
Home-page: https://github.com/cavia-io/coupling
Author: Ye Yang
Author-email: ye.yang@cavia.io
License: MIT
Platform: Posix; MacOS X; Windows
Classifier: Development Status :: 4 - Beta
Classifier: Intended Audience :: Developers
Classifier: License :: OSI Approved :: MIT License
Classifier: Operating System :: OS Independent
Classifier: Topic :: Software Development :: Libraries
Classifier: Topic :: Software Development :: Libraries :: Python Modules
Classifier: Programming Language :: Python
Classifier: Programming Language :: Python :: 3
Classifier: Programming Language :: Python :: 3.5
Classifier: Programming Language :: Python :: 3.6
Classifier: Programming Language :: Python :: 3.7
Requires-Python: >=3.6.5
Requires-Dist: lxml
Requires-Dist: paramiko
Requires-Dist: jsonpath-ng
Requires-Dist: redis
